headerindexer/__init__.py
headerindexer/_hi_objects/__init__.py
headerindexer/_hi_objects/data_obj/__init__.py
headerindexer/_hi_objects/data_obj/_errors.py
headerindexer/_hi_objects/data_obj/_workings.py
headerindexer/_hi_objects/pycolims_0_2_0/__init__.py
headerindexer/_hi_objects/pycolims_0_2_0/menus/Menu_Factory.py
headerindexer/_hi_objects/pycolims_0_2_0/menus/__init__.py
headerindexer/_hi_objects/pycolims_0_2_0/menus/_base_menu_template.py
headerindexer/_hi_objects/pycolims_0_2_0/menus/_menu_engine.py
headerindexer/_hi_objects/pycolims_0_2_0/menus/_menu_multi.py
headerindexer/_hi_objects/pycolims_0_2_0/menus/_menu_single.py
headerindexer/_hi_objects/pycolims_0_2_0/menus/data/__init__.py
headerindexer/_hi_objects/pycolims_0_2_0/menus/data/_command.py
headerindexer/_hi_objects/pycolims_0_2_0/menus/data/_pages.py
headerindexer/_hi_objects/pycolims_0_2_0/menus/data/_terminal.py
headerindexer/_hi_objects/pycolims_0_2_0/menus/data/_work.py
headerindexer/_hi_objects/pycolims_0_2_0/menus/data/data_factory.py
headerindexer/_hi_objects/pycolims_0_2_0/menus/data/customtypes/__init__.py
headerindexer/_hi_objects/pycolims_0_2_0/menus/data/customtypes/_cremental_list.py
headerindexer-0.1.5.dist-info/LICENSE
headerindexer-0.1.5.dist-info/METADATA
headerindexer-0.1.5.dist-info/WHEEL
headerindexer-0.1.5.dist-info/top_level.txt
headerindexer-0.1.5.dist-info/RECORD
