Metadata-Version: 2.1
Name: headerindexer
Version: 0.1.5
Summary: A system to bind aliases to indexes of headers in a matrix
Home-page: https://github.com/dpazavalos/headerindexer
Author: Daniel Paz Avalos
Author-email: me@dpazavalos.dev
License: UNKNOWN
Platform: UNKNOWN
Classifier: Programming Language :: Python :: 3.5
Classifier: License :: OSI Approved :: MIT License
Classifier: Operating System :: OS Independent
